richillcapital_infrastructure-0.0.2.dist-info/METADATA
richillcapital_infrastructure-0.0.2.dist-info/WHEEL
richillcapital_infrastructure-0.0.2.dist-info/licenses/LICENSE
richillcapital_infrastructure/__init__.py
richillcapital_infrastructure/persistence/__init__.py
richillcapital_infrastructure/persistence/schemas/__init__.py
richillcapital_infrastructure-0.0.2.dist-info/RECORD
