Metadata-Version: 2.1
Name: richillcapital-infrastructure
Version: 0.0.2
Author-Email: Mengsyue Amao Tsai <mengsyue.tsai@outlook.com>
License: MIT
Requires-Python: >=3.11
Requires-Dist: pyodbc>=4.0.39
Requires-Dist: sqlalchemy>=2.0.21
Requires-Dist: richillcapital-core>=0.0.1
